setup.cfg
setup.py
pyramid_webapp_scaffold/__init__.py
pyramid_webapp_scaffold.egg-info/PKG-INFO
pyramid_webapp_scaffold.egg-info/SOURCES.txt
pyramid_webapp_scaffold.egg-info/dependency_links.txt
pyramid_webapp_scaffold.egg-info/entry_points.txt
pyramid_webapp_scaffold.egg-info/requires.txt
pyramid_webapp_scaffold.egg-info/top_level.txt
pyramid_webapp_scaffold.egg-info/zip-safe
pyramid_webapp_scaffold/scaffolds/__init__.py