Metadata-Version: 1.0
Name: pyramid_webapp_scaffold
Version: 0.1.1
Summary: Pyramid Webapp Scaffold
Home-page: UNKNOWN
Author: Larry Weya
Author-email: larryweya@gmail.com
License: MIT
Keywords: pyramid scaffold webapp
Platform: UNKNOWN
